cncf_serverless_workflow/__init__.py
cncf_serverless_workflow/test_workflow_engine.py
cncf_serverless_workflow/test_workflow_validator.py
cncf_serverless_workflow/workflow_engine.py
cncf_serverless_workflow/workflow_example.yaml
cncf_serverless_workflow/workflow_schema.yaml
cncf_serverless_workflow/workflow_validator.py
cncf_serverless_workflow-0.1.2.dist-info/licenses/LICENSE
cncf_serverless_workflow-0.1.2.dist-info/METADATA
cncf_serverless_workflow-0.1.2.dist-info/WHEEL
cncf_serverless_workflow-0.1.2.dist-info/top_level.txt
cncf_serverless_workflow-0.1.2.dist-info/RECORD
