Metadata-Version: 2.4
Name: cncf-serverless-workflow
Version: 0.1.2
Summary: CNCF Serverless Workflow v1.0 validator and executor
Home-page: https://github.com/rvergis/cncf-serverless-workflow-python-v1
Author: Ron Vergis
License: MIT
Classifier: Programming Language :: Python :: 3
Classifier: License :: OSI Approved :: MIT License
Classifier: Operating System :: OS Independent
License-File: LICENSE
Requires-Dist: pyyaml
Requires-Dist: jq
Requires-Dist: jsonschema
Requires-Dist: pytest
Dynamic: author
Dynamic: classifier
Dynamic: description
Dynamic: description-content-type
Dynamic: home-page
Dynamic: license
Dynamic: license-file
Dynamic: requires-dist
Dynamic: summary
